setup.py
TNaLaGmes.egg-info/PKG-INFO
TNaLaGmes.egg-info/SOURCES.txt
TNaLaGmes.egg-info/dependency_links.txt
TNaLaGmes.egg-info/top_level.txt
tnalagmes/__init__.py
tnalagmes/intents.py
tnalagmes/data/__init__.py
tnalagmes/data/oregon_trail_data.py
tnalagmes/data/template_data.py
tnalagmes/data/zombie_survival_data.py
tnalagmes/engines/__init__.py
tnalagmes/engines/intentworld.py
tnalagmes/engines/oregon.py
tnalagmes/engines/oregon75.py
tnalagmes/engines/oregon78.py
tnalagmes/engines/textadventurer.py
tnalagmes/engines/textwarrior.py
tnalagmes/games/__init__.py
tnalagmes/games/dummy.py
tnalagmes/games/oregon_trail.py
tnalagmes/games/zombie.py
tnalagmes/lang/__init__.py
tnalagmes/lang/format_common.py
tnalagmes/lang/format_de.py
tnalagmes/lang/format_en.py
tnalagmes/lang/format_fr.py
tnalagmes/lang/format_it.py
tnalagmes/lang/format_pt.py
tnalagmes/lang/format_sv.py
tnalagmes/lang/parse_common.py
tnalagmes/lang/parse_de.py
tnalagmes/lang/parse_en.py
tnalagmes/lang/parse_es.py
tnalagmes/lang/parse_fr.py
tnalagmes/lang/parse_it.py
tnalagmes/lang/parse_pt.py
tnalagmes/lang/parse_sv.py
tnalagmes/lang/phonemes_en.py
tnalagmes/lang/translate.py
tnalagmes/models/__init__.py
tnalagmes/models/agents.py
tnalagmes/models/battle.py
tnalagmes/models/objects.py
tnalagmes/models/world.py
tnalagmes/util/__init__.py
tnalagmes/util/log.py
tnalagmes/util/nlp.py
tnalagmes/util/phonemes.py
tnalagmes/util/signal.py
tnalagmes/util/time.py