Metadata-Version: 1.0
Name: TNaLaGmes
Version: 0.1
Summary: TNaLaGmes is a Toolbox for Natural Language Games
Home-page: https://github.com/JarbasAl/TNaLaGmes
Author: jarbasAI
Author-email: jarbasai@mailfence.com
License: Apache2.0
Platform: UNKNOWN
